GESS/.Rhistory
GESS/GESSPercentIDMatrix.py
GESS/GESS_Tutorial.ipynb
GESS/GESS_core.py
GESS/GESSfinder.py
GESS/GESSmatricise.py
GESS/README.md
GESS/__init__.py
GESS/Testing/Batch_compare_ages.sh
GESS/Testing/GESS_mass_unittest.sh
GESS/Testing/InterpretGESSTesting.py
GESS/Utils/GESSargs.py
GESS/Utils/GetH5Genes.py
GESS/Utils/HandleH5s.py
gess-0.1.1.dist-info/METADATA
gess-0.1.1.dist-info/WHEEL
gess-0.1.1.dist-info/licenses/LICENSE
gess-0.1.1.dist-info/RECORD
